{
    "backend": "django",
    "db_name": "",
    "db_pass": "",
    "db_type": "mysql",
    "db_user": "",
    "dbms": "1",
    "description": "generated product",
    "design": "soft-ui-dashboard",
    "docker": "1",
    "err_code": 0,
    "frontend": "",
    "github_repo": "https://github.com/appseed-projects/dad2f1f6-2f6e-4a40-83fb-972c7ef4ec3d",
    "heroku": "0",
    "pattern": "mvc",
    "pro": "0",
    "task_id": "dad2f1f6-2f6e-4a40-83fb-972c7ef4ec3d",
    "task_info": "Upload Sources [0%] - 340 files",
    "task_output": "dad2f1f6-2f6e-4a40-83fb-972c7ef4ec3d.zip",
    "task_result": "SUCCESS",
    "task_state": "RUNNING",
    "task_ts_end": "2022-06-08-13-45-55",
    "task_ts_start": "2022-06-08-13-45-51"
}